mmsws/mmsws/__init__.py
mmsws-0.1.0.dist-info/LICENSE.md
mmsws-0.1.0.dist-info/METADATA
mmsws-0.1.0.dist-info/WHEEL
mmsws-0.1.0.dist-info/RECORD
