Metadata-Version: 2.1
Name: mmsws
Version: 0.1.0
Summary: A Python API for LASP MMS Science Data Center (SDC) web services
Home-page: https://github.com/tien-vo/mmsws
License: GPL-3.0-only
Keywords: space plasma,heliophysics,plasma,plasma physics,science,magnetospheric multiscale mission
Author: Tien Vo
Author-email: tvo.work@proton.me
Requires-Python: >=3.12,<4.0
Classifier: Development Status :: 1 - Planning
Classifier: Intended Audience :: Science/Research
Classifier: License :: OSI Approved :: GNU General Public License v3 (GPLv3)
Classifier: Natural Language :: English
Classifier: Operating System :: MacOS
Classifier: Operating System :: Microsoft :: Windows
Classifier: Operating System :: Unix
Classifier: Programming Language :: Python
Classifier: Programming Language :: Python :: 3
Classifier: Programming Language :: Python :: 3.12
Classifier: Topic :: Scientific/Engineering :: Physics
Project-URL: Repository, https://github.com/tien-vo/mmsws
